<aetgt:getResponse xmlns:aetgt="http://schemas.active-endpoints.com/appmodules/repository/2010/10/avrepository.xsd"
                   xmlns:types1="http://schemas.active-endpoints.com/appmodules/repository/2010/10/avrepository.xsd">
   <types1:Item>
      <types1:EntryId>EpciZBpDUQbgdwU-gt-16160401-2021-08-13T10:41:44.492Z::po.xml</types1:EntryId>
      <types1:Name>POEntityDetails</types1:Name>
      <types1:ParentFlowIds>0EKZhHwzZsMBw8j-gt-10100679-2021-08-13T10:41:44.987Z::pd.xml,Ev18pNz6HKoJBUh-gt-16161461-2021-08-13T10:41:47.493Z::pd.xml,gdyOoMdtlI20hEL-gt-1645194-2023-08-23T10:01:31.03Z::pd.xml,kRCU7uMydx2CGeF-gt-312811-2023-07-13T10:25:49.164Z::pd.xml,nKf3eFhBJQWSwxF-gt-1936702-2022-07-19T19:36:46.214Z::pd.xml,T7dwcnPCOkSSHCw-gt-23276945-2023-03-29T09:54:53.734Z::pd.xml</types1:ParentFlowIds>
      <types1:MimeType>application/xml+processobject</types1:MimeType>
      <types1:Description/>
      <types1:AppliesTo/>
      <types1:Tags/>
      <types1:VersionLabel>1.0</types1:VersionLabel>
      <types1:State>CURRENT</types1:State>
      <types1:ProcessGroup/>
      <types1:CreatedBy>benarji-vistra-tst</types1:CreatedBy>
      <types1:CreationDate>2021-08-13T10:41:44Z</types1:CreationDate>
      <types1:ModifiedBy>veerabh-vistra-tst</types1:ModifiedBy>
      <types1:ModificationDate>2022-10-12T10:47:48Z</types1:ModificationDate>
      <types1:PublicationStatus>unpublished</types1:PublicationStatus>
      <types1:AutosaveExists>false</types1:AutosaveExists>
      <types1:Entry>
         <processObject xmlns="http://schemas.active-endpoints.com/appmodules/screenflow/2011/06/avosHostEnvironment.xsd"
                        displayName="POEntityDetails"
                        isByCopy="true"
                        name="POEntityDetails">
            <description/>
            <tags/>
            <detail>
               <field label="RevEntity"
                      name="RevEntity"
                      nullable="true"
                      required="false"
                      type="string"/>
               <field label="RefType"
                      name="RefType"
                      nullable="true"
                      required="false"
                      type="string"/>
               <field label="AddrCode"
                      name="AddrCode"
                      nullable="true"
                      required="false"
                      type="string"/>
               <field label="BillAddress"
                      name="BillAddress"
                      nullable="true"
                      required="false"
                      type="string"/>
               <field label="cText"
                      name="cText"
                      nullable="true"
                      required="false"
                      type="string"/>
               <field label="cType"
                      name="cType"
                      nullable="true"
                      required="false"
                      type="string"/>
               <field label="Active"
                      name="Active"
                      nullable="true"
                      required="false"
                      type="string"/>
               <field label="AddrType"
                      name="AddrType"
                      nullable="true"
                      required="false"
                      type="string"/>
               <field label="AddrNr"
                      name="AddrNr"
                      nullable="true"
                      required="false"
                      type="string"/>
               <field label="City"
                      name="City"
                      nullable="true"
                      required="false"
                      type="string"/>
               <field label="Country"
                      name="Country"
                      nullable="true"
                      required="false"
                      type="string"/>
               <field label="PostalCode"
                      name="PostalCode"
                      nullable="true"
                      required="false"
                      type="string"/>
               <field label="Address"
                      name="Address"
                      nullable="true"
                      required="false"
                      type="string"/>
               <field label="RefMasterAdminGroup"
                      name="RefMasterAdminGroup"
                      nullable="true"
                      required="false"
                      type="string"/>
               <field label="RefMasterName"
                      name="RefMasterName"
                      nullable="true"
                      required="false"
                      type="string"/>
               <field label="RefCode"
                      name="RefCode"
                      nullable="true"
                      required="false"
                      type="string"/>
               <field label="Language"
                      name="Language"
                      nullable="true"
                      required="false"
                      type="string"/>
               <field label="FileStatus"
                      name="FileStatus"
                      nullable="true"
                      required="false"
                      type="string"/>
               <field label="OrgCode"
                      name="OrgCode"
                      nullable="true"
                      required="false"
                      type="string"/>
               <field label="MatterStatus"
                      name="MatterStatus"
                      nullable="true"
                      required="false"
                      type="string"/>
               <field label="BalanceCur"
                      name="BalanceCur"
                      nullable="true"
                      required="false"
                      type="string"/>
               <field label="OrgUnit1"
                      name="OrgUnit1"
                      nullable="true"
                      required="false"
                      type="string"/>
               <field label="CurCode"
                      name="CurCode"
                      nullable="true"
                      required="false"
                      type="string"/>
               <field label="Region"
                      name="Region"
                      nullable="true"
                      required="false"
                      type="string"/>
               <field label="Address2"
                      name="Address2"
                      nullable="true"
                      required="false"
                      type="string"/>
               <field label="Address3"
                      name="Address3"
                      nullable="true"
                      required="false"
                      type="string"/>
               <field label="Address4"
                      name="Address4"
                      nullable="true"
                      required="false"
                      type="string"/>
               <field label="Address5"
                      name="Address5"
                      nullable="true"
                      required="false"
                      type="string"/>
               <field label="Payterm"
                      name="Payterm"
                      nullable="true"
                      required="false"
                      type="string"/>
               <field label="PaytermTag"
                      name="PaytermTag"
                      nullable="true"
                      required="false"
                      type="string"/>
               <field label="EmailInvoice"
                      name="EmailInvoice"
                      nullable="true"
                      required="false"
                      type="string"/>
               <field label="EmailInvoiceCC"
                      name="EmailInvoiceCC"
                      nullable="true"
                      required="false"
                      type="string"/>
               <field label="EmailInvoiceReminder"
                      name="EmailInvoiceReminder"
                      nullable="true"
                      required="false"
                      type="string"/>
               <field label="EmailOther"
                      name="EmailOther"
                      nullable="true"
                      required="false"
                      type="string"/>
               <field label="AltName"
                      name="AltName"
                      nullable="true"
                      required="false"
                      type="string"/>
            </detail>
         </processObject>
      </types1:Entry>
      <types1:GUID>9pfIZtTCho6eam7UAD0HUg</types1:GUID>
      <types1:DisplayName>POEntityDetails</types1:DisplayName>
   </types1:Item>
   <types1:CurrentServerDateTime>2023-09-16T18:19:15.391Z</types1:CurrentServerDateTime>
</aetgt:getResponse>
