{
  "objectInfo" : {
    "id" : "hYBaWTd9wiOkvVi7F9foqX",
    "name" : "process_GetAll_VForce_MAIN",
    "type" : "PROCESS",
    "metadata" : {
      "modelVersion" : {
        "major" : 1,
        "minor" : 0
      },
      "repoInfo" : {
        "repoHandle" : "EIDhMBu8zbgdwUi-gt-1155862-2021-12-13T04:57:04.495Z::pd.xml"
      },
      "contextAttributes" : null,
      "additionalInfo" : {
        "description" : "",
        "contentType" : "application/json; charset=utf-8",
        "documentState" : "VALID"
      }
    }
  },
  "dataFileExtension" : "xml",
  "objectRefs" : [ {
    "id" : "0pvQET5ohVgkyWKfTCGNS3",
    "name" : "process_GetContact",
    "type" : "PROCESS",
    "metadata" : {
      "modelVersion" : {
        "major" : 1,
        "minor" : 0
      },
      "repoInfo" : {
        "repoHandle" : "JZx1XmgaabclvAh-gt-11550985-2021-12-09T15:30:35.57Z::pd.xml"
      },
      "contextAttributes" : null,
      "additionalInfo" : {
        "description" : "",
        "contentType" : "application/json; charset=utf-8",
        "documentState" : "VALID"
      }
    },
    "path" : "/Explore/VIP_US_Integration/Processes VForce"
  }, {
    "id" : "bOFOoUr3KomhFLN7Nah4uD",
    "name" : "PO-VFAccount",
    "type" : "PROCESS_OBJECT",
    "metadata" : {
      "modelVersion" : {
        "major" : 1,
        "minor" : 0
      },
      "repoInfo" : {
        "repoHandle" : "bchspiRASmvD4te-gt-5936307-2021-12-02T19:42:37.018Z::po.xml"
      },
      "contextAttributes" : null,
      "additionalInfo" : {
        "description" : "",
        "contentType" : "application/json; charset=utf-8",
        "documentState" : "VALID"
      }
    },
    "path" : "/Explore/VIP_US_Integration/ProcessObjects"
  }, {
    "id" : "2v8kzALzXITeM3j4bYG3Qk",
    "name" : "process_GetAccountDetails",
    "type" : "PROCESS",
    "metadata" : {
      "modelVersion" : {
        "major" : 1,
        "minor" : 0
      },
      "repoInfo" : {
        "repoHandle" : "3VQU8lpDqotxGom-gt-11501406-2021-12-09T14:21:18.876Z::pd.xml"
      },
      "contextAttributes" : null,
      "additionalInfo" : {
        "description" : "",
        "contentType" : "application/json; charset=utf-8",
        "documentState" : "VALID"
      }
    },
    "path" : "/Explore/VIP_US_Integration/Processes VForce"
  }, {
    "id" : "3AFOA0PsJ6dcReNZta4f8q",
    "name" : "PO-VFContact",
    "type" : "PROCESS_OBJECT",
    "metadata" : {
      "modelVersion" : {
        "major" : 1,
        "minor" : 0
      },
      "repoInfo" : {
        "repoHandle" : "ypmXbeMVX3cjk91-gt-1225785-2021-12-13T07:15:34.403Z::po.xml"
      },
      "contextAttributes" : null,
      "additionalInfo" : {
        "description" : "",
        "contentType" : "application/json; charset=utf-8",
        "documentState" : "VALID"
      }
    },
    "path" : "/Explore/VIP_US_Integration/ProcessObjects"
  }, {
    "id" : "00KxBybvU0vlxiRVlBmYsM",
    "name" : "PO-User",
    "type" : "PROCESS_OBJECT",
    "metadata" : {
      "modelVersion" : {
        "major" : 1,
        "minor" : 0
      },
      "repoInfo" : {
        "repoHandle" : "1pqrzYLnzYLnzYL-gt-14180886-2022-01-12T19:01:38.44Z::po.xml"
      },
      "contextAttributes" : null,
      "additionalInfo" : {
        "description" : "",
        "contentType" : "application/json; charset=utf-8",
        "documentState" : "VALID"
      }
    },
    "path" : "/Explore/Z_HarshalB"
  }, {
    "id" : "hDVO92UUDWugMz8gKVVdQA",
    "name" : "Process_User_details",
    "type" : "PROCESS",
    "metadata" : {
      "modelVersion" : {
        "major" : 1,
        "minor" : 0
      },
      "repoInfo" : {
        "repoHandle" : "tvlp6oIuQaaabcm-gt-21605931-2022-01-14T15:17:52.32Z::pd.xml"
      },
      "contextAttributes" : null,
      "additionalInfo" : {
        "description" : "",
        "contentType" : "application/json; charset=utf-8",
        "documentState" : "VALID"
      }
    },
    "path" : "/Explore/VIP_US_Integration/Processes VForce"
  }, {
    "id" : "9mlrXLLOFIXkt9y0guBbmJ",
    "name" : "process_US_ErrorLog",
    "type" : "PROCESS",
    "metadata" : {
      "modelVersion" : {
        "major" : 1,
        "minor" : 0
      },
      "repoInfo" : {
        "repoHandle" : "8H36I1dq2ME9paa-gt-1155731-2021-12-13T06:03:29.568Z::pd.xml"
      },
      "contextAttributes" : null,
      "additionalInfo" : {
        "description" : "",
        "contentType" : "application/json; charset=utf-8",
        "documentState" : "VALID"
      }
    },
    "path" : "/Explore/VIP_US_Integration/Processes"
  }, {
    "id" : "4pTPBYUyQkRjSsJ8zYJvuN",
    "name" : "PO-VFOpportunityLineItem",
    "type" : "PROCESS_OBJECT",
    "metadata" : {
      "modelVersion" : {
        "major" : 1,
        "minor" : 0
      },
      "repoInfo" : {
        "repoHandle" : "hIppppppppppppp-gt-11459623-2021-12-10T15:53:42.124Z::po.xml"
      },
      "contextAttributes" : null,
      "additionalInfo" : {
        "description" : "",
        "contentType" : "application/json; charset=utf-8",
        "documentState" : "VALID"
      }
    },
    "path" : "/Explore/VIP_US_Integration/ProcessObjects"
  }, {
    "id" : "1rDGSIlM8Jwk4l5tKGdGa7",
    "name" : "PO-User",
    "type" : "PROCESS_OBJECT",
    "metadata" : {
      "modelVersion" : {
        "major" : 1,
        "minor" : 0
      },
      "repoInfo" : {
        "repoHandle" : "xxYxQ2Tp5OjG4ab-gt-15859224-2022-01-14T13:17:33.379Z::po.xml"
      },
      "contextAttributes" : null,
      "additionalInfo" : {
        "description" : "",
        "contentType" : "application/json; charset=utf-8",
        "documentState" : "VALID"
      }
    },
    "path" : "/Explore/VIP_US_Integration/ProcessObjects"
  }, {
    "id" : "0OIMngchMUFlrPyhXB0Aax",
    "name" : "process_GetOpportunityProduct",
    "type" : "PROCESS",
    "metadata" : {
      "modelVersion" : {
        "major" : 1,
        "minor" : 0
      },
      "repoInfo" : {
        "repoHandle" : "GFaaaaaaaaaaaaa-gt-10525883-2021-12-09T14:54:13.524Z::pd.xml"
      },
      "contextAttributes" : null,
      "additionalInfo" : {
        "description" : "",
        "contentType" : "application/json; charset=utf-8",
        "documentState" : "VALID"
      }
    },
    "path" : "/Explore/VIP_US_Integration/Processes VForce"
  }, {
    "id" : "2KhAYZLEDlygPcoKa7RAaW",
    "name" : "process_GetOpportunity",
    "type" : "PROCESS",
    "metadata" : {
      "modelVersion" : {
        "major" : 1,
        "minor" : 0
      },
      "repoInfo" : {
        "repoHandle" : "Hbci0seGbciZBpD-gt-14094398-2021-12-09T17:09:30.547Z::pd.xml"
      },
      "contextAttributes" : null,
      "additionalInfo" : {
        "description" : "",
        "contentType" : "application/json; charset=utf-8",
        "documentState" : "VALID"
      }
    },
    "path" : "/Explore/VIP_US_Integration/Processes VForce"
  }, {
    "id" : "7bzhlNon2CWl5JJ64znsEa",
    "name" : "PO-VFOpportunity",
    "type" : "PROCESS_OBJECT",
    "metadata" : {
      "modelVersion" : {
        "major" : 1,
        "minor" : 0
      },
      "repoInfo" : {
        "repoHandle" : "yjllCYAOTMneBjr-gt-11478988-2021-12-10T15:27:47.389Z::po.xml"
      },
      "contextAttributes" : null,
      "additionalInfo" : {
        "description" : "",
        "contentType" : "application/json; charset=utf-8",
        "documentState" : "VALID"
      }
    },
    "path" : "/Explore/VIP_US_Integration/ProcessObjects"
  }, {
    "id" : "3NUe9IluUUng4Y2pV8lo4M",
    "name" : "PO-EventDetials",
    "type" : "PROCESS_OBJECT",
    "metadata" : {
      "modelVersion" : {
        "major" : 1,
        "minor" : 0
      },
      "repoInfo" : {
        "repoHandle" : "M1reAFLK2D86Cjq-gt-2116107-2021-12-14T05:35:26.623Z::po.xml"
      },
      "contextAttributes" : null,
      "additionalInfo" : {
        "description" : "",
        "contentType" : "application/json; charset=utf-8",
        "documentState" : "VALID"
      }
    },
    "path" : "/Explore/VIP_US_Integration/ProcessObjects"
  } ]
}