{
  "objectInfo" : {
    "id" : "bbOXMeh0JeJkuj45JTCtCp",
    "name" : "AppSvcJournalEntryCreateRequestConfirmation-In",
    "type" : "AI_CONNECTION",
    "metadata" : {
      "modelVersion" : {
        "major" : 1,
        "minor" : 0
      },
      "repoInfo" : {
        "repoHandle" : "5nBQ9WYzr3tfUbb-gt-6715860-2022-09-14T08:26:07.912Z::conn.xml"
      },
      "contextAttributes" : null,
      "additionalInfo" : {
        "description" : "https://api.sap.com/api/OP_JOURNALENTRYCREATEREQUESTCONF_IN/overview",
        "contentType" : "application/json; charset=utf-8",
        "documentState" : "VALID"
      }
    }
  },
  "dataFileExtension" : "xml",
  "objectRefs" : [ {
    "id" : "35hVXVDix7ThcsdpVVSgEV",
    "name" : "SvcJournalEntryCreateRequestConfirmation-In",
    "type" : "AI_SERVICE_CONNECTOR",
    "metadata" : {
      "modelVersion" : {
        "major" : 1,
        "minor" : 0
      },
      "repoInfo" : {
        "repoHandle" : "wMbgbdoPVm5Y6tM-gt-6715676-2022-09-14T08:26:03.55Z::svc.xml"
      },
      "contextAttributes" : null,
      "additionalInfo" : {
        "description" : "https://api.sap.com/api/OP_JOURNALENTRYCREATEREQUESTCONF_IN/overview",
        "contentType" : "application/json; charset=utf-8",
        "documentState" : "VALID"
      }
    },
    "path" : "/Explore/Generic SAP Processes/Connectors (Custom)"
  } ]
}