{
  "objectInfo" : {
    "id" : "afFo8bsepoBbEwruqpQxgJ",
    "name" : "AppSvcBusinessPartnerA2X",
    "type" : "AI_CONNECTION",
    "metadata" : {
      "modelVersion" : {
        "major" : 1,
        "minor" : 0
      },
      "repoInfo" : {
        "repoHandle" : "i0lHww43dtQR6kb-gt-24777155-2022-08-18T16:11:26.141Z::conn.xml"
      },
      "contextAttributes" : null,
      "additionalInfo" : {
        "description" : "",
        "contentType" : "application/json; charset=utf-8",
        "documentState" : "VALID"
      }
    }
  },
  "dataFileExtension" : "xml",
  "updateTime" : "2023-09-21T11:18:19.917Z",
  "objectRefs" : [ {
    "id" : "4wKsFLFB8sRcMTAlSTTH6V",
    "name" : "svcBusinessPartnerA2X",
    "type" : "AI_SERVICE_CONNECTOR",
    "metadata" : {
      "modelVersion" : {
        "major" : 1,
        "minor" : 0
      },
      "repoInfo" : {
        "repoHandle" : "bdutaaabbgdoGsF-gt-24777024-2022-08-18T16:11:24.024Z::svc.xml"
      },
      "contextAttributes" : null,
      "additionalInfo" : {
        "description" : "https://api.sap.com/api/API_BUSINESS_PARTNER/overview",
        "contentType" : "application/json; charset=utf-8",
        "documentState" : "VALID"
      }
    },
    "path" : "/Explore/Generic SAP Processes/Connectors (Custom)"
  } ]
}