<aetgt:getResponse xmlns:aetgt="http://schemas.active-endpoints.com/appmodules/repository/2010/10/avrepository.xsd"
                   xmlns:types1="http://schemas.active-endpoints.com/appmodules/repository/2010/10/avrepository.xsd">
   <types1:Item>
      <types1:EntryId>yXf66vfXjISUXL8-gt-24260931-2022-01-18T09:58:20.397Z::conn.xml</types1:EntryId>
      <types1:Name>US-AppCon-JsonWtiter</types1:Name>
      <types1:ParentFlowIds>5Y6tMFyglsO7RY6-gt-24261041-2022-01-18T09:58:25.904Z::pd.xml,9VtsDaaabdvhxiQ-gt-24261053-2022-01-18T09:58:25.973Z::pd.xml,msvE3C7snSDg8SO-gt-24261077-2022-01-18T09:58:26.207Z::pd.xml,rmumf6S3wOLIFvu-gt-24260975-2022-01-18T09:58:22.286Z::pd.xml,X89SfSmbduaa-gt-17828620-2022-01-18T09:58:24.793Z::pd.xml,ZigdpIO3M4WwOC2-gt-24261029-2022-01-18T09:58:25.825Z::pd.xml</types1:ParentFlowIds>
      <types1:MimeType>application/xml+connection</types1:MimeType>
      <types1:Description>Success and Failed Logging for API 01 to 03</types1:Description>
      <types1:AppliesTo/>
      <types1:Tags>.agent:VIP_IICS_SA_SG_ONPREM_GROUP</types1:Tags>
      <types1:VersionLabel>1.0</types1:VersionLabel>
      <types1:State>CURRENT</types1:State>
      <types1:ProcessGroup/>
      <types1:CreatedBy>rudolph.boshoff@vistra.com.SAML</types1:CreatedBy>
      <types1:CreationDate>2022-01-18T09:58:20Z</types1:CreationDate>
      <types1:ModifiedBy>rudolph.boshoff@vistra.com.SAML</types1:ModifiedBy>
      <types1:ModificationDate>2022-03-04T09:35:48Z</types1:ModificationDate>
      <types1:PublicationStatus>published</types1:PublicationStatus>
      <types1:PublishedBy>rudolph.boshoff@vistra.com.SAML</types1:PublishedBy>
      <types1:PublicationDate>2022-03-04T09:36:14Z</types1:PublicationDate>
      <types1:PublishedContributionId>project:/rt.connection/US-AppCon-JsonWtiter/US-AppCon-JsonWtiter.conn.xml</types1:PublishedContributionId>
      <types1:AutosaveExists>false</types1:AutosaveExists>
      <types1:Entry>
         <connection xmlns="http://schemas.informatica.com/socrates/data-services/2014/04/avosConnections.xsd"
                     displayName="US-AppCon-JsonWtiter"
                     label="US-AppCon-JsonWtiter"
                     name="US-AppCon-JsonWtiter">
            <description>Success and Failed Logging for API 01 to 03</description>
            <tags>.agent:VIP_IICS_SA_SG_ONPREM_GROUP</tags>
            <agent>VIP_IICS_SA_SG_ONPREM_GROUP</agent>
            <attributes/>
            <producers>
               <producer enabled="true" name="JsonWriter-Opportunity" typeName="FileWriter">
                  <description>Use this event target to write output to a file.</description>
                  <attributes>
                     <attribute encrypted="false"
                                name="directoryName"
                                value="e:\data\vforceevents\"/>
                     <attribute encrypted="false" name="fileExist" value="TryRename"/>
                     <attribute encrypted="false" name="moveExisting" value=""/>
                     <attribute encrypted="false" name="eagerDeleteTargetFile" value="true"/>
                     <attribute encrypted="false" name="tempPrefix" value=""/>
                     <attribute encrypted="false" name="tempFileName" value=""/>
                     <attribute encrypted="false" name="forceWrites" value="true"/>
                     <attribute encrypted="false" name="bufferSize" value=""/>
                     <attribute encrypted="false" name="charset" value=""/>
                  </attributes>
               </producer>
            </producers>
            <javaConnector xmlns="http://schemas.informatica.com/appmodules/screenflow/2014/04/avosConnectors.xsd"
                           agentOnly="true"
                           plugin="Camel"
                           supportsConnectionTest="true"
                           supportsDataPreview="false"
                           supportsOData="false"
                           type="File"
                           uuid="ac000300-d9fe-11e4-8830-0800200c9a66">
               <description>Provides connections to file monitoring brokers.</description>
            </javaConnector>
         </connection>
      </types1:Entry>
      <types1:GUID>6qWzesXeEs2ee967mLUyWy</types1:GUID>
      <types1:DisplayName>US-AppCon-JsonWtiter</types1:DisplayName>
   </types1:Item>
   <types1:CurrentServerDateTime>2023-10-15T13:22:43.05Z</types1:CurrentServerDateTime>
</aetgt:getResponse>
